etc_jupyterlab_notebook_state_provider/__init__.py
etc_jupyterlab_notebook_state_provider/_version.py
etc_jupyterlab_notebook_state_provider/application.py
etc_jupyterlab_notebook_state_provider/handlers.py
etc_jupyterlab_notebook_state_provider/labextension/build_log.json
etc_jupyterlab_notebook_state_provider/labextension/package.json
etc_jupyterlab_notebook_state_provider/labextension/schemas/@educational-technology-collective/etc_jupyterlab_notebook_state_provider/package.json.orig
etc_jupyterlab_notebook_state_provider/labextension/schemas/@educational-technology-collective/etc_jupyterlab_notebook_state_provider/plugin.json
etc_jupyterlab_notebook_state_provider/labextension/static/lib_index_js.a4a3e5d1150e7a5b5586.js
etc_jupyterlab_notebook_state_provider/labextension/static/lib_index_js.a4a3e5d1150e7a5b5586.js.map
etc_jupyterlab_notebook_state_provider/labextension/static/remoteEntry.e2d4f614a13c9a73d829.js
etc_jupyterlab_notebook_state_provider/labextension/static/remoteEntry.e2d4f614a13c9a73d829.js.map
etc_jupyterlab_notebook_state_provider/labextension/static/style.js
etc_jupyterlab_notebook_state_provider/labextension/static/style_index_js.f1e41f76c7e386a2a0b8.js
etc_jupyterlab_notebook_state_provider/labextension/static/style_index_js.f1e41f76c7e386a2a0b8.js.map
etc_jupyterlab_notebook_state_provider/labextension/static/vendors-node_modules_css-loader_dist_runtime_api_js-node_modules_css-loader_dist_runtime_cssW-72eba1.0fdbe371458a254e2588.js
etc_jupyterlab_notebook_state_provider/labextension/static/vendors-node_modules_css-loader_dist_runtime_api_js-node_modules_css-loader_dist_runtime_cssW-72eba1.0fdbe371458a254e2588.js.map
etc_jupyterlab_notebook_state_provider-2.0.9.data/data/etc/jupyter/jupyter_notebook_config.d/etc_jupyterlab_notebook_state_provider.json
etc_jupyterlab_notebook_state_provider-2.0.9.data/data/etc/jupyter/jupyter_server_config.d/etc_jupyterlab_notebook_state_provider.json
etc_jupyterlab_notebook_state_provider-2.0.9.dist-info/LICENSE
etc_jupyterlab_notebook_state_provider-2.0.9.dist-info/METADATA
etc_jupyterlab_notebook_state_provider-2.0.9.dist-info/WHEEL
etc_jupyterlab_notebook_state_provider-2.0.9.dist-info/top_level.txt
etc_jupyterlab_notebook_state_provider-2.0.9.dist-info/RECORD
